{
 "1": {
  "ts": "2026-06-23",
  "seen": [
   "H&M Cotton Jersey Sleepsuit",
   "Kyte Baby Zipper Footie",
   "Burt's Bees Baby Organic Cotton Beekeeper Footie",
   "Little Me Footie and Hat Set",
   "Magnetic Me Modal Footie",
   "Aden + Anais Essentials Zip Sleepsuit"
  ],
  "list": [
   {
    "name": "Little Me Footie and Hat Set",
    "why": "High-quality, thick cotton fabrics perfect for Indian winters and often available via premium international shipping.",
    "pros": [
     "Extremely soft premium cotton",
     "Adorable, detailed designs"
    ],
    "cons": [
     "Often uses snaps instead of two-way zips"
    ],
    "price": 2800,
    "currency": "INR",
    "links": {
     "india": "https://www.amazon.in/s?k=Little%20Me%20Footie%20and%20Hat%20Set",
     "uk": "https://www.next.co.uk/search?w=Little%20Me%20Footie%20and%20Hat%20Set",
     "canada": "https://www.amazon.ca/s?k=Little%20Me%20Footie%20and%20Hat%20Set"
    }
   },
   {
    "name": "Magnetic Me Modal Footie",
    "why": "Features magnetic closures that make middle-of-the-night diaper changes effortless for tired parents.",
    "pros": [
     "Incredibly fast to dress/undress",
     "Buttery soft modal fabric"
    ],
    "cons": [
     "Expensive compared to standard sleepsuits"
    ],
    "price": 3500,
    "currency": "INR",
    "links": {
     "india": "https://www.amazon.in/s?k=Magnetic%20Me%20Modal%20Footie",
     "uk": "https://www.next.co.uk/search?w=Magnetic%20Me%20Modal%20Footie",
     "canada": "https://www.amazon.ca/s?k=Magnetic%20Me%20Modal%20Footie"
    }
   },
   {
    "name": "Aden + Anais Essentials Zip Sleepsuit",
    "why": "Renowned for breathable muslin-blend fabrics that regulate temperature well in varying indoor climates.",
    "pros": [
     "Excellent breathability",
     "Durable fabric that softens with every wash"
    ],
    "cons": [
     "Limited color patterns available"
    ],
    "price": 2200,
    "currency": "INR",
    "links": {
     "india": "https://www.amazon.in/s?k=Aden%20%2B%20Anais%20Essentials%20Zip%20Sleepsuit",
     "uk": "https://www.next.co.uk/search?w=Aden%20%2B%20Anais%20Essentials%20Zip%20Sleepsuit",
     "canada": "https://www.amazon.ca/s?k=Aden%20%2B%20Anais%20Essentials%20Zip%20Sleepsuit"
    }
   }
  ]
 },
 "2": {
  "ts": "2026-06-23",
  "seen": [
   "Mori Clever Zip Bodysuit 2-pk",
   "Mothercare Bodysuits 5-pk",
   "H&M Cotton Bodysuit 5-pk",
   "Jojo Maman Bébé Baby Bodysuit with Fold-Back Mittens",
   "Next Baby Long Sleeve Mittened Bodysuits (3 Pack)",
   "Burt's Bees Baby Organic Cotton Long Sleeve Bodysuit",
   "The Children's Place Long Sleeve Bodysuits with Mittens",
   "Little Me Long Sleeve Mittened Bodysuit",
   "Gap Baby Organic Cotton Foldover-Mitten Bodysuit"
  ],
  "list": [
   {
    "name": "The Children's Place Long Sleeve Bodysuits with Mittens",
    "why": "Reliable, affordable staple available widely in North America with soft, durable cotton blend fabric.",
    "pros": [
     "Fold-over mittens are integrated securely",
     "Retains shape well after multiple washes"
    ],
    "cons": [
     "Cotton is standard rather than organic"
    ],
    "price": 1800,
    "currency": "INR",
    "links": {
     "india": "https://www.amazon.in/s?k=The%20Children's%20Place%20Long%20Sleeve%20Bodysuits%20with%20Mittens",
     "uk": "https://www.next.co.uk/search?w=The%20Children's%20Place%20Long%20Sleeve%20Bodysuits%20with%20Mittens",
     "canada": "https://www.amazon.ca/s?k=The%20Children's%20Place%20Long%20Sleeve%20Bodysuits%20with%20Mittens"
    }
   },
   {
    "name": "Little Me Long Sleeve Mittened Bodysuit",
    "why": "Premium boutique quality featuring thoughtful designs and extra-soft fabric perfect for winter comfort.",
    "pros": [
     "Exceptional fabric softness",
     "High-quality snap closures"
    ],
    "cons": [
     "Higher price point per unit"
    ],
    "price": 2800,
    "currency": "INR",
    "links": {
     "india": "https://www.amazon.in/s?k=Little%20Me%20Long%20Sleeve%20Mittened%20Bodysuit",
     "uk": "https://www.next.co.uk/search?w=Little%20Me%20Long%20Sleeve%20Mittened%20Bodysuit",
     "canada": "https://www.amazon.ca/s?k=Little%20Me%20Long%20Sleeve%20Mittened%20Bodysuit"
    }
   },
   {
    "name": "Gap Baby Organic Cotton Foldover-Mitten Bodysuit",
    "why": "A classic winter essential from a trusted brand known for consistent sizing and skin-friendly organic materials.",
    "pros": [
     "GOTS certified organic cotton",
     "Stretchy fabric makes dressing easier"
    ],
    "cons": [
     "Limited availability in physical Indian stores"
    ],
    "price": 2200,
    "currency": "INR",
    "links": {
     "india": "https://www.amazon.in/s?k=Gap%20Baby%20Organic%20Cotton%20Foldover-Mitten%20Bodysuit",
     "uk": "https://www.next.co.uk/search?w=Gap%20Baby%20Organic%20Cotton%20Foldover-Mitten%20Bodysuit",
     "canada": "https://www.amazon.ca/s?k=Gap%20Baby%20Organic%20Cotton%20Foldover-Mitten%20Bodysuit"
    }
   }
  ]
 },
 "3": {
  "ts": "2026-06-23",
  "seen": [
   "Mori Stay-on Socks 3-pk",
   "FirstCry Newborn Socks 6-pk",
   "H&M Cotton-blend Socks 5-pack",
   "GAP Baby Organic Cotton Crew Socks",
   "Boody Baby Organic Bamboo Socks",
   "Jojo Maman Bébé Stay-On Baby Socks",
   "Little Me Newborn Bootie Socks",
   "Zutano Stay-On Baby Booties"
  ],
  "list": [
   {
    "name": "Jojo Maman Bébé Stay-On Baby Socks",
    "why": "Engineered with a ribbed knit and special construction to prevent them from slipping off active newborn feet.",
    "pros": [
     "Excellent stay-on capability",
     "Soft, high-quality cotton blend"
    ],
    "cons": [
     "More expensive than basic multipacks"
    ],
    "price": 1200,
    "currency": "INR",
    "links": {
     "india": "https://www.amazon.in/s?k=Jojo%20Maman%20B%C3%A9b%C3%A9%20Stay-On%20Baby%20Socks",
     "uk": "https://www.next.co.uk/search?w=Jojo%20Maman%20B%C3%A9b%C3%A9%20Stay-On%20Baby%20Socks",
     "canada": "https://www.amazon.ca/s?k=Jojo%20Maman%20B%C3%A9b%C3%A9%20Stay-On%20Baby%20Socks"
    }
   },
   {
    "name": "Little Me Newborn Bootie Socks",
    "why": "Designed specifically for newborns with a plush, sock-bootie hybrid feel that provides extra warmth for winter babies.",
    "pros": [
     "Extra cozy for winter",
     "Non-constricting elastic"
    ],
    "cons": [
     "Bulkier than standard socks"
    ],
    "price": 950,
    "currency": "INR",
    "links": {
     "india": "https://www.amazon.in/s?k=Little%20Me%20Newborn%20Bootie%20Socks",
     "uk": "https://www.next.co.uk/search?w=Little%20Me%20Newborn%20Bootie%20Socks",
     "canada": "https://www.amazon.ca/s?k=Little%20Me%20Newborn%20Bootie%20Socks"
    }
   },
   {
    "name": "Zutano Stay-On Baby Booties",
    "why": "A cult-favorite in North America that uses a snap closure to ensure they never fall off, perfect for chilly Indian winte",
    "pros": [
     "Impossible for baby to kick off",
     "Durable fleece options available"
    ],
    "cons": [
     "Requires international shipping or import"
    ],
    "price": 1800,
    "currency": "INR",
    "links": {
     "india": "https://www.amazon.in/s?k=Zutano%20Stay-On%20Baby%20Booties",
     "uk": "https://www.next.co.uk/search?w=Zutano%20Stay-On%20Baby%20Booties",
     "canada": "https://www.amazon.ca/s?k=Zutano%20Stay-On%20Baby%20Booties"
    }
   }
  ]
 },
 "4": {
  "ts": "2026-06-23",
  "seen": [
   "Mamas & Papas Welcome to the World Knitted Hat",
   "Mothercare Newborn Cotton Ribbed Beanies",
   "Aden + Anais Essentials Cotton Muslin Knotted Baby Hat",
   "Jojo Maman Bébé Jersey Cotton Baby Hat",
   "FirstCry BabyHug Winter Woolen Cap with Ear Flaps",
   "Gap Baby Organic Cotton Bear Ear Beanie"
  ],
  "list": [
   {
    "name": "Jojo Maman Bébé Jersey Cotton Baby Hat",
    "why": "A high-quality, soft cotton option from the UK that is perfect for layering under heavier hoods during Indian winters.",
    "pros": [
     "Extremely soft organic cotton",
     "Excellent shape retention after washes"
    ],
    "cons": [
     "Requires international shipping or proxy service"
    ],
    "price": 1200,
    "currency": "INR",
    "links": {
     "india": "https://www.amazon.in/s?k=Jojo%20Maman%20B%C3%A9b%C3%A9%20Jersey%20Cotton%20Baby%20Hat",
     "uk": "https://www.next.co.uk/search?w=Jojo%20Maman%20B%C3%A9b%C3%A9%20Jersey%20Cotton%20Baby%20Hat",
     "canada": "https://www.amazon.ca/s?k=Jojo%20Maman%20B%C3%A9b%C3%A9%20Jersey%20Cotton%20Baby%20Hat"
    }
   },
   {
    "name": "FirstCry BabyHug Winter Woolen Cap with Ear Flaps",
    "why": "Provides essential coverage for newborn ears against chilly drafts, widely available across India.",
    "pros": [
     "Includes protective ear flaps",
     "Affordable and easily accessible"
    ],
    "cons": [
     "Synthetic material may not be as breathable as organic cotton"
    ],
    "price": 350,
    "currency": "INR",
    "links": {
     "india": "https://www.amazon.in/s?k=FirstCry%20BabyHug%20Winter%20Woolen%20Cap%20with%20Ear%20Flaps",
     "uk": "https://www.next.co.uk/search?w=FirstCry%20BabyHug%20Winter%20Woolen%20Cap%20with%20Ear%20Flaps",
     "canada": "https://www.amazon.ca/s?k=FirstCry%20BabyHug%20Winter%20Woolen%20Cap%20with%20Ear%20Flaps"
    }
   },
   {
    "name": "Gap Baby Organic Cotton Bear Ear Beanie",
    "why": "A popular, durable choice available globally that offers superior warmth with a cute design for winter.",
    "pros": [
     "Stretchy fit for growing heads",
     "Thick, high-quality knit fabric"
    ],
    "cons": [
     "Can be slightly bulky for indoor use"
    ],
    "price": 1800,
    "currency": "INR",
    "links": {
     "india": "https://www.amazon.in/s?k=Gap%20Baby%20Organic%20Cotton%20Bear%20Ear%20Beanie",
     "uk": "https://www.next.co.uk/search?w=Gap%20Baby%20Organic%20Cotton%20Bear%20Ear%20Beanie",
     "canada": "https://www.amazon.ca/s?k=Gap%20Baby%20Organic%20Cotton%20Bear%20Ear%20Beanie"
    }
   }
  ]
 },
 "5": {
  "ts": "2026-06-23",
  "seen": [
   "Mori Cellular Blanket",
   "Mamas & Papas Knitted Blanket",
   "Aden + Anais Essentials Muslin Swaddle Blanket",
   "The White Company Hydrocotton Baby Blanket",
   "Little West Street Organic Cotton Knitted Blanket",
   "Snuggle Me Organic Cotton Stroller Blanket",
   "Gro Company Gro-snug Swaddle to Sleeping Bag",
   "Masilo Organic Cotton Muslin Quilt"
  ],
  "list": [
   {
    "name": "Snuggle Me Organic Cotton Stroller Blanket",
    "why": "Offers premium organic breathability which is ideal for layering during milder Indian winters without causing overheatin",
    "pros": [
     "GOTS certified organic cotton",
     "Excellent thermal regulation"
    ],
    "cons": [
     "Limited color variety"
    ],
    "price": 4500,
    "currency": "INR",
    "links": {
     "india": "https://www.amazon.in/s?k=Snuggle%20Me%20Organic%20Cotton%20Stroller%20Blanket",
     "uk": "https://www.next.co.uk/search?w=Snuggle%20Me%20Organic%20Cotton%20Stroller%20Blanket",
     "canada": "https://www.amazon.ca/s?k=Snuggle%20Me%20Organic%20Cotton%20Stroller%20Blanket"
    }
   },
   {
    "name": "Gro Company Gro-snug Swaddle to Sleeping Bag",
    "why": "A practical 2-in-1 solution that keeps the baby secure and warm during the transition from swaddling to sleeping bags.",
    "pros": [
     "Versatile swaddle-to-bag design",
     "Hip-healthy ergonomic shape"
    ],
    "cons": [
     "Requires sizing up as baby grows"
    ],
    "price": 3200,
    "currency": "INR",
    "links": {
     "india": "https://www.amazon.in/s?k=Gro%20Company%20Gro-snug%20Swaddle%20to%20Sleeping%20Bag",
     "uk": "https://www.next.co.uk/search?w=Gro%20Company%20Gro-snug%20Swaddle%20to%20Sleeping%20Bag",
     "canada": "https://www.amazon.ca/s?k=Gro%20Company%20Gro-snug%20Swaddle%20to%20Sleeping%20Bag"
    }
   },
   {
    "name": "Masilo Organic Cotton Muslin Quilt",
    "why": "A high-quality, locally available option in India that provides extra warmth through its multi-layered muslin constructi",
    "pros": [
     "Softens with every wash",
     "Available locally in India"
    ],
    "cons": [
     "Thinner than traditional wool quilts"
    ],
    "price": 2800,
    "currency": "INR",
    "links": {
     "india": "https://www.amazon.in/s?k=Masilo%20Organic%20Cotton%20Muslin%20Quilt",
     "uk": "https://www.next.co.uk/search?w=Masilo%20Organic%20Cotton%20Muslin%20Quilt",
     "canada": "https://www.amazon.ca/s?k=Masilo%20Organic%20Cotton%20Muslin%20Quilt"
    }
   }
  ]
 },
 "6": {
  "ts": "2026-06-23",
  "seen": [
   "Stokke Flexi Bath",
   "Fisher-Price 4-in-1 Sling 'n Seat Tub",
   "Skip Hop Moby Smart Sling 3-Stage Tub",
   "Angelcare Baby Bath Support",
   "Summer Infant My Bath Seat",
   "Munchkin White Hot Inflatable Safety Duck Tub"
  ],
  "list": [
   {
    "name": "Angelcare Baby Bath Support",
    "why": "An ergonomic, mesh-based design that drains instantly and dries quickly, preventing mold growth.",
    "pros": [
     "Lightweight and easy to store",
     "Soft-touch material is comfortable for newborn skin"
    ],
    "cons": [
     "Does not hold water; requires use inside a larger tub or sink"
    ],
    "price": 3500,
    "currency": "INR",
    "links": {
     "india": "https://www.amazon.in/s?k=Angelcare%20Baby%20Bath%20Support",
     "uk": "https://www.next.co.uk/search?w=Angelcare%20Baby%20Bath%20Support",
     "canada": "https://www.amazon.ca/s?k=Angelcare%20Baby%20Bath%20Support"
    }
   },
   {
    "name": "Summer Infant My Bath Seat",
    "why": "Provides excellent 360-degree support for babies who are just starting to sit, ideal for later in the winter season.",
    "pros": [
     "Suction cups keep it securely in place",
     "Spacious design allows for easy cleaning"
    ],
    "cons": [
     "Only suitable once the baby has good head and neck control"
    ],
    "price": 4200,
    "currency": "INR",
    "links": {
     "india": "https://www.amazon.in/s?k=Summer%20Infant%20My%20Bath%20Seat",
     "uk": "https://www.next.co.uk/search?w=Summer%20Infant%20My%20Bath%20Seat",
     "canada": "https://www.amazon.ca/s?k=Summer%20Infant%20My%20Bath%20Seat"
    }
   },
   {
    "name": "Munchkin White Hot Inflatable Safety Duck Tub",
    "why": "A space-saving, portable option that is perfect for travel and features a safety sensor to prevent overheating.",
    "pros": [
     "Compact when deflated for easy storage",
     "Textured bottom prevents baby from slipping"
    ],
    "cons": [
     "Requires manual inflation before every use"
    ],
    "price": 2800,
    "currency": "INR",
    "links": {
     "india": "https://www.amazon.in/s?k=Munchkin%20White%20Hot%20Inflatable%20Safety%20Duck%20Tub",
     "uk": "https://www.next.co.uk/search?w=Munchkin%20White%20Hot%20Inflatable%20Safety%20Duck%20Tub",
     "canada": "https://www.amazon.ca/s?k=Munchkin%20White%20Hot%20Inflatable%20Safety%20Duck%20Tub"
    }
   }
  ]
 },
 "7": {
  "ts": "2026-06-23",
  "seen": [
   "Little Unicorn Cotton Muslin 3-pk",
   "Masilo / Mulmul Organic Muslin (India)",
   "ErgoPouch Cocoon Swaddle Bag (0.2 - 2.5 TOG)",
   "SwaddleMe Original Swaddle",
   "Nested Bean Zen Swaddle",
   "Kyte Baby Swaddle Blanket",
   "Mamaearth Organic Cotton Swaddle Wrap",
   "Copper Pearl Swaddle Blanket"
  ],
  "list": [
   {
    "name": "Kyte Baby Swaddle Blanket",
    "why": "Crafted from ultra-soft bamboo rayon, this provides exceptional temperature regulation for a winter newborn.",
    "pros": [
     "Extremely soft and breathable fabric",
     "Stretchy material makes for an easy, snug wrap"
    ],
    "cons": [
     "Requires delicate washing to maintain fabric quality"
    ],
    "price": 3800,
    "currency": "INR",
    "links": {
     "india": "https://www.amazon.in/s?k=Kyte%20Baby%20Swaddle%20Blanket",
     "uk": "https://www.next.co.uk/search?w=Kyte%20Baby%20Swaddle%20Blanket",
     "canada": "https://www.amazon.ca/s?k=Kyte%20Baby%20Swaddle%20Blanket"
    }
   },
   {
    "name": "Mamaearth Organic Cotton Swaddle Wrap",
    "why": "A highly accessible, high-quality organic cotton option widely available in the Indian market.",
    "pros": [
     "Hypoallergenic and gentle on newborn skin",
     "Large dimensions allow for versatile use as a nursing cover"
    ],
    "cons": [
     "Fabric is thinner than premium bamboo alternatives"
    ],
    "price": 900,
    "currency": "INR",
    "links": {
     "india": "https://www.amazon.in/s?k=Mamaearth%20Organic%20Cotton%20Swaddle%20Wrap",
     "uk": "https://www.next.co.uk/search?w=Mamaearth%20Organic%20Cotton%20Swaddle%20Wrap",
     "canada": "https://www.amazon.ca/s?k=Mamaearth%20Organic%20Cotton%20Swaddle%20Wrap"
    }
   },
   {
    "name": "Copper Pearl Swaddle Blanket",
    "why": "These premium knit swaddles offer a modern aesthetic with a unique blend of fabric that holds a tight swaddle.",
    "pros": [
     "Excellent stretch and recovery",
     "Trendy, modern patterns and prints"
    ],
    "cons": [
     "Can feel slightly heavy for very warm indoor environments"
    ],
    "price": 3200,
    "currency": "INR",
    "links": {
     "india": "https://www.amazon.in/s?k=Copper%20Pearl%20Swaddle%20Blanket",
     "uk": "https://www.next.co.uk/search?w=Copper%20Pearl%20Swaddle%20Blanket",
     "canada": "https://www.amazon.ca/s?k=Copper%20Pearl%20Swaddle%20Blanket"
    }
   }
  ]
 },
 "8": {
  "ts": "2026-06-23",
  "seen": [
   "Muslin Tree Cotton Muslin Washcloths",
   "aden + anais Essentials Washcloth Set",
   "Bey Bee Organic Cotton Washcloths",
   "LuvLap Baby Washcloths (Pack of 6)",
   "Burt's Bees Baby Washcloths (3-Pack)",
   "Hudson Baby Animal Face Washcloths"
  ],
  "list": [
   {
    "name": "LuvLap Baby Washcloths (Pack of 6)",
    "why": "A highly accessible, budget-friendly option in India featuring soft, absorbent cotton terry fabric suitable for daily ne",
    "pros": [
     "Highly absorbent cotton material",
     "Easily available on major Indian e-commerce sites"
    ],
    "cons": [
     "Fabric can feel slightly less soft after many machine washes"
    ],
    "price": 350,
    "currency": "INR",
    "links": {
     "india": "https://www.amazon.in/s?k=LuvLap%20Baby%20Washcloths%20(Pack%20of%206)",
     "uk": "https://www.next.co.uk/search?w=LuvLap%20Baby%20Washcloths%20(Pack%20of%206)",
     "canada": "https://www.amazon.ca/s?k=LuvLap%20Baby%20Washcloths%20(Pack%20of%206)"
    }
   },
   {
    "name": "Burt's Bees Baby Washcloths (3-Pack)",
    "why": "A premium, organic cotton knit option available via international shipping that is exceptionally gentle on newborn skin.",
    "pros": [
     "GOTS-certified organic cotton",
     "Durable quality that maintains softness"
    ],
    "cons": [
     "Higher cost due to international shipping and import duties"
    ],
    "price": 2200,
    "currency": "INR",
    "links": {
     "india": "https://www.amazon.in/s?k=Burt's%20Bees%20Baby%20Washcloths%20(3-Pack)",
     "uk": "https://www.next.co.uk/search?w=Burt's%20Bees%20Baby%20Washcloths%20(3-Pack)",
     "canada": "https://www.amazon.ca/s?k=Burt's%20Bees%20Baby%20Washcloths%20(3-Pack)"
    }
   },
   {
    "name": "Hudson Baby Animal Face Washcloths",
    "why": "These offer a thicker, plush texture and cute designs that are popular for their longevity and high-quality construction",
    "pros": [
     "Thick, plush fabric is very gentle",
     "Fun, engaging designs for bath time"
    ],
    "cons": [
     "Takes longer to air dry than thin muslin cloths"
    ],
    "price": 1200,
    "currency": "INR",
    "links": {
     "india": "https://www.amazon.in/s?k=Hudson%20Baby%20Animal%20Face%20Washcloths",
     "uk": "https://www.next.co.uk/search?w=Hudson%20Baby%20Animal%20Face%20Washcloths",
     "canada": "https://www.amazon.ca/s?k=Hudson%20Baby%20Animal%20Face%20Washcloths"
    }
   }
  ]
 },
 "9": {
  "ts": "2026-06-23",
  "seen": [
   "Snuggle Me Organic Changing Pad Cover",
   "IKEA VÄDRA Changing Mat Cover",
   "Carter's Cotton Jersey Changing Pad Cover",
   "Burt's Bees Baby Organic Cotton Changing Pad Cover",
   "Mothercare Jersey Changing Mat Cover",
   "Little West Street Muslin Changing Pad Cover"
  ],
  "list": [
   {
    "name": "Burt's Bees Baby Organic Cotton Changing Pad Cover",
    "why": "Renowned for extremely soft, breathable organic cotton that is gentle on newborn skin during winter.",
    "pros": [
     "GOTS certified organic cotton",
     "High-quality elastic for a snug, safe fit"
    ],
    "cons": [
     "Can shrink slightly if not washed according to label"
    ],
    "price": 2800,
    "currency": "INR",
    "links": {
     "india": "https://www.amazon.in/s?k=Burt's%20Bees%20Baby%20Organic%20Cotton%20Changing%20Pad%20Cover",
     "uk": "https://www.next.co.uk/search?w=Burt's%20Bees%20Baby%20Organic%20Cotton%20Changing%20Pad%20Cover",
     "canada": "https://www.amazon.ca/s?k=Burt's%20Bees%20Baby%20Organic%20Cotton%20Changing%20Pad%20Cover"
    }
   },
   {
    "name": "Mothercare Jersey Changing Mat Cover",
    "why": "A widely trusted, durable option available in India that provides a cozy, warm surface for diaper changes.",
    "pros": [
     "Soft jersey fabric provides extra comfort",
     "Easy to machine wash and quick drying"
    ],
    "cons": [
     "Limited color options compared to boutique brands"
    ],
    "price": 1200,
    "currency": "INR",
    "links": {
     "india": "https://www.amazon.in/s?k=Mothercare%20Jersey%20Changing%20Mat%20Cover",
     "uk": "https://www.next.co.uk/search?w=Mothercare%20Jersey%20Changing%20Mat%20Cover",
     "canada": "https://www.amazon.ca/s?k=Mothercare%20Jersey%20Changing%20Mat%20Cover"
    }
   },
   {
    "name": "Little West Street Muslin Changing Pad Cover",
    "why": "Specifically designed for the Indian climate, these muslin covers are breathable yet soft enough for cooler months.",
    "pros": [
     "Gets softer with every wash",
     "Beautiful, aesthetic prints"
    ],
    "cons": [
     "Muslin fabric is thinner than jersey cotton"
    ],
    "price": 1500,
    "currency": "INR",
    "links": {
     "india": "https://www.amazon.in/s?k=Little%20West%20Street%20Muslin%20Changing%20Pad%20Cover",
     "uk": "https://www.next.co.uk/search?w=Little%20West%20Street%20Muslin%20Changing%20Pad%20Cover",
     "canada": "https://www.amazon.ca/s?k=Little%20West%20Street%20Muslin%20Changing%20Pad%20Cover"
    }
   }
  ]
 },
 "10": {
  "ts": "2026-06-23",
  "seen": [
   "KeaBabies Bandana Bibs 8-pk",
   "Mushie Bandana Bibs 2-pk",
   "Mom’s Home Bandana Bibs 8-pk",
   "Aden + Anais Essentials Muslin Snap Bibs",
   "Tommee Tippee Closer to Nature Milk Feeding Bibs",
   "The Moms Co. Organic Cotton Bibs",
   "Copper Pearl Bandana Bibs",
   "Bibado Coverall Weaning Bib",
   "Mamaearth Organic Cotton Bibs"
  ],
  "list": [
   {
    "name": "Copper Pearl Bandana Bibs",
    "why": "Renowned for their exceptional absorbency and stylish prints that double as a trendy outfit accessory.",
    "pros": [
     "Highly absorbent front fabric",
     "Adjustable nickel-free snaps"
    ],
    "cons": [
     "Higher price point than basic options"
    ],
    "price": 2200,
    "currency": "INR",
    "links": {
     "india": "https://www.amazon.in/s?k=Copper%20Pearl%20Bandana%20Bibs",
     "uk": "https://www.next.co.uk/search?w=Copper%20Pearl%20Bandana%20Bibs",
     "canada": "https://www.amazon.ca/s?k=Copper%20Pearl%20Bandana%20Bibs"
    }
   },
   {
    "name": "Bibado Coverall Weaning Bib",
    "why": "Essential for the start of solid foods, this long-sleeved bib keeps the baby's clothing completely clean during messy wi",
    "pros": [
     "Full coverage design",
     "Stain-resistant material"
    ],
    "cons": [
     "Requires more effort to put on"
    ],
    "price": 1800,
    "currency": "INR",
    "links": {
     "india": "https://www.amazon.in/s?k=Bibado%20Coverall%20Weaning%20Bib",
     "uk": "https://www.next.co.uk/search?w=Bibado%20Coverall%20Weaning%20Bib",
     "canada": "https://www.amazon.ca/s?k=Bibado%20Coverall%20Weaning%20Bib"
    }
   },
   {
    "name": "Mamaearth Organic Cotton Bibs",
    "why": "A widely available, accessible choice in India that uses skin-friendly organic cotton suitable for sensitive newborn ski",
    "pros": [
     "Soft breathable fabric",
     "Easy to wash and maintain"
    ],
    "cons": [
     "Less absorbent than multi-layer fleece-backed bibs"
    ],
    "price": 600,
    "currency": "INR",
    "links": {
     "india": "https://www.amazon.in/s?k=Mamaearth%20Organic%20Cotton%20Bibs",
     "uk": "https://www.next.co.uk/search?w=Mamaearth%20Organic%20Cotton%20Bibs",
     "canada": "https://www.amazon.ca/s?k=Mamaearth%20Organic%20Cotton%20Bibs"
    }
   }
  ]
 },
 "11": {
  "ts": "2026-06-23",
  "seen": [
   "Mamas & Papas Heritage Velvet Dress & Bloomer Set",
   "The Children's Place Baby Boys Formal Vest Set",
   "Jam & Honey Baby Unisex Formal Romper",
   "Jojo Maman Bébé Tartan Dungaree & Shirt Set",
   "Little West Street Baby Boy Formal Romper Set",
   "Janie and Jack Velvet Bow Dress Set"
  ],
  "list": [
   {
    "name": "Jojo Maman Bébé Tartan Dungaree & Shirt Set",
    "why": "A classic, timeless British winter formal aesthetic that is both warm and comfortable for newborns.",
    "pros": [
     "Soft cotton lining for sensitive skin",
     "Traditional high-quality festive design"
    ],
    "cons": [
     "Expensive international shipping from UK"
    ],
    "price": 4200,
    "currency": "INR",
    "links": {
     "india": "https://www.amazon.in/s?k=Jojo%20Maman%20B%C3%A9b%C3%A9%20Tartan%20Dungaree%20%26%20Shirt%20Set",
     "uk": "https://www.next.co.uk/search?w=Jojo%20Maman%20B%C3%A9b%C3%A9%20Tartan%20Dungaree%20%26%20Shirt%20Set",
     "canada": "https://www.amazon.ca/s?k=Jojo%20Maman%20B%C3%A9b%C3%A9%20Tartan%20Dungaree%20%26%20Shirt%20Set"
    }
   },
   {
    "name": "Little West Street Baby Boy Formal Romper Set",
    "why": "A premium Indian brand that offers high-quality cotton fabrics suitable for the Indian winter climate.",
    "pros": [
     "Breathable organic cotton material",
     "Easy-access snap buttons for diaper changes"
    ],
    "cons": [
     "Limited stock availability in retail stores"
    ],
    "price": 2800,
    "currency": "INR",
    "links": {
     "india": "https://www.amazon.in/s?k=Little%20West%20Street%20Baby%20Boy%20Formal%20Romper%20Set",
     "uk": "https://www.next.co.uk/search?w=Little%20West%20Street%20Baby%20Boy%20Formal%20Romper%20Set",
     "canada": "https://www.amazon.ca/s?k=Little%20West%20Street%20Baby%20Boy%20Formal%20Romper%20Set"
    }
   },
   {
    "name": "Janie and Jack Velvet Bow Dress Set",
    "why": "Known for high-end boutique quality, this set provides a sophisticated look for formal winter occasions.",
    "pros": [
     "Exceptional fabric durability",
     "Includes matching accessories"
    ],
    "cons": [
     "Requires delicate hand washing"
    ],
    "price": 6500,
    "currency": "INR",
    "links": {
     "india": "https://www.amazon.in/s?k=Janie%20and%20Jack%20Velvet%20Bow%20Dress%20Set",
     "uk": "https://www.next.co.uk/search?w=Janie%20and%20Jack%20Velvet%20Bow%20Dress%20Set",
     "canada": "https://www.amazon.ca/s?k=Janie%20and%20Jack%20Velvet%20Bow%20Dress%20Set"
    }
   }
  ]
 },
 "12": {
  "ts": "2026-06-23",
  "seen": [
   "Mamas & Papas Essential Cotton Sleepsuit",
   "Kyte BABY Zipper Footie",
   "FirstCry BabyHug Interlock Sleepsuit",
   "Burt's Bees Baby Organic Cotton Beekeeper Wearable Blanket",
   "Little Me Footie and Hat Set",
   "SuperBottoms Organic Cotton Sleepsuit"
  ],
  "list": [
   {
    "name": "Burt's Bees Baby Organic Cotton Beekeeper Wearable Blanket",
    "why": "A safe, GOTS-certified organic cotton option that keeps babies warm during Indian winters without the risk of loose blan",
    "pros": [
     "Breathable organic material",
     "Excellent durability after multiple washes"
    ],
    "cons": [
     "Higher price point due to import"
    ],
    "price": 3200,
    "currency": "INR",
    "links": {
     "india": "https://www.amazon.in/s?k=Burt's%20Bees%20Baby%20Organic%20Cotton%20Beekeeper%20Wearable%20Blanket",
     "uk": "https://www.next.co.uk/search?w=Burt's%20Bees%20Baby%20Organic%20Cotton%20Beekeeper%20Wearable%20Blanket",
     "canada": "https://www.amazon.ca/s?k=Burt's%20Bees%20Baby%20Organic%20Cotton%20Beekeeper%20Wearable%20Blanket"
    }
   },
   {
    "name": "Little Me Footie and Hat Set",
    "why": "Renowned for high-quality, soft knits that provide extra warmth, making them perfect for the slightly cooler North India",
    "pros": [
     "Features adorable prints",
     "Includes a matching cap for heat retention"
    ],
    "cons": [
     "Available primarily through international shipping"
    ],
    "price": 2800,
    "currency": "INR",
    "links": {
     "india": "https://www.amazon.in/s?k=Little%20Me%20Footie%20and%20Hat%20Set",
     "uk": "https://www.next.co.uk/search?w=Little%20Me%20Footie%20and%20Hat%20Set",
     "canada": "https://www.amazon.ca/s?k=Little%20Me%20Footie%20and%20Hat%20Set"
    }
   },
   {
    "name": "SuperBottoms Organic Cotton Sleepsuit",
    "why": "A highly-rated Indian brand that uses GOTS-certified cotton, specifically designed for the Indian climate and skin sensi",
    "pros": [
     "Convenient snap buttons for easy diaper changes",
     "Soft, chemical-free fabric"
    ],
    "cons": [
     "Limited pattern variety compared to global brands"
    ],
    "price": 1200,
    "currency": "INR",
    "links": {
     "india": "https://www.amazon.in/s?k=SuperBottoms%20Organic%20Cotton%20Sleepsuit",
     "uk": "https://www.next.co.uk/search?w=SuperBottoms%20Organic%20Cotton%20Sleepsuit",
     "canada": "https://www.amazon.ca/s?k=SuperBottoms%20Organic%20Cotton%20Sleepsuit"
    }
   }
  ]
 },
 "13": {
  "ts": "2026-06-23",
  "seen": [
   "H&M Cotton Jersey Baby Blanket",
   "Aden + Anais Essentials Muslin Swaddle Blanket",
   "FirstCry Babyhug Anti-Scratch Mittens & Booties Set",
   "Mamas & Papas Welcome to the World Knitted Cardigan",
   "Kyte BABY Sleep Bag (0.5 Tog)",
   "Carter's Baby Zip-Up Fleece Pram Suit"
  ],
  "list": [
   {
    "name": "Mamas & Papas Welcome to the World Knitted Cardigan",
    "why": "A high-quality, essential layering piece for Indian winters that keeps newborns cozy without overheating.",
    "pros": [
     "Breathable cotton-rich fabric",
     "Durable snap-button closures"
    ],
    "cons": [
     "Requires delicate hand-wash care"
    ],
    "price": 2800,
    "currency": "INR",
    "links": {
     "india": "https://www.amazon.in/s?k=Mamas%20%26%20Papas%20Welcome%20to%20the%20World%20Knitted%20Cardigan",
     "uk": "https://www.next.co.uk/search?w=Mamas%20%26%20Papas%20Welcome%20to%20the%20World%20Knitted%20Cardigan",
     "canada": "https://www.amazon.ca/s?k=Mamas%20%26%20Papas%20Welcome%20to%20the%20World%20Knitted%20Cardigan"
    }
   },
   {
    "name": "Kyte BABY Sleep Bag (0.5 Tog)",
    "why": "The gold standard for safe sleep, featuring ultra-soft bamboo rayon that regulates temperature effectively.",
    "pros": [
     "Incredibly soft material",
     "Double zipper for easy diaper changes"
    ],
    "cons": [
     "Premium pricing"
    ],
    "price": 4500,
    "currency": "INR",
    "links": {
     "india": "https://www.amazon.in/s?k=Kyte%20BABY%20Sleep%20Bag%20(0.5%20Tog)",
     "uk": "https://www.next.co.uk/search?w=Kyte%20BABY%20Sleep%20Bag%20(0.5%20Tog)",
     "canada": "https://www.amazon.ca/s?k=Kyte%20BABY%20Sleep%20Bag%20(0.5%20Tog)"
    }
   },
   {
    "name": "Carter's Baby Zip-Up Fleece Pram Suit",
    "why": "Perfect for keeping the baby warm during outdoor outings in the cooler months of November.",
    "pros": [
     "Full coverage for warmth",
     "Easy zip-up design"
    ],
    "cons": [
     "Can feel bulky for car seat use"
    ],
    "price": 3200,
    "currency": "INR",
    "links": {
     "india": "https://www.amazon.in/s?k=Carter's%20Baby%20Zip-Up%20Fleece%20Pram%20Suit",
     "uk": "https://www.next.co.uk/search?w=Carter's%20Baby%20Zip-Up%20Fleece%20Pram%20Suit",
     "canada": "https://www.amazon.ca/s?k=Carter's%20Baby%20Zip-Up%20Fleece%20Pram%20Suit"
    }
   }
  ]
 },
 "14": {
  "ts": "2026-06-23",
  "seen": [
   "H&M Cotton Jersey Booties",
   "Jojo Maman Bébé Stay-On Booties",
   "FirstCry BabyHug Soft Booties",
   "Zutano Unisex Baby Fleece Booties",
   "Moromini Organic Cotton Ribbed Booties",
   "Little West Street Cotton Baby Booties"
  ],
  "list": [
   {
    "name": "Zutano Unisex Baby Fleece Booties",
    "why": "The gold standard for staying on due to their unique snap-button side closure system.",
    "pros": [
     "Stays securely on even the wiggliest feet",
     "Soft, warm fleece material perfect for winter"
    ],
    "cons": [
     "Higher price point compared to standard cotton socks"
    ],
    "price": 2800,
    "currency": "INR",
    "links": {
     "india": "https://www.amazon.in/s?k=Zutano%20Unisex%20Baby%20Fleece%20Booties",
     "uk": "https://www.next.co.uk/search?w=Zutano%20Unisex%20Baby%20Fleece%20Booties",
     "canada": "https://www.amazon.ca/s?k=Zutano%20Unisex%20Baby%20Fleece%20Booties"
    }
   },
   {
    "name": "Moromini Organic Cotton Ribbed Booties",
    "why": "High-quality European craftsmanship with extra-long cuffs that keep them from slipping off.",
    "pros": [
     "Excellent organic material quality",
     "Extra-long cuffs provide a secure, cozy fit"
    ],
    "cons": [
     "Requires international shipping from Europe or UK"
    ],
    "price": 1600,
    "currency": "INR",
    "links": {
     "india": "https://www.amazon.in/s?k=Moromini%20Organic%20Cotton%20Ribbed%20Booties",
     "uk": "https://www.next.co.uk/search?w=Moromini%20Organic%20Cotton%20Ribbed%20Booties",
     "canada": "https://www.amazon.ca/s?k=Moromini%20Organic%20Cotton%20Ribbed%20Booties"
    }
   },
   {
    "name": "Little West Street Cotton Baby Booties",
    "why": "A premium Indian brand offering soft, breathable, and stylish options available locally.",
    "pros": [
     "Soft 100% cotton fabric is gentle on newborn skin",
     "Easily accessible within the Indian market"
    ],
    "cons": [
     "Less grip than fleece options for crawling infants"
    ],
    "price": 800,
    "currency": "INR",
    "links": {
     "india": "https://www.amazon.in/s?k=Little%20West%20Street%20Cotton%20Baby%20Booties",
     "uk": "https://www.next.co.uk/search?w=Little%20West%20Street%20Cotton%20Baby%20Booties",
     "canada": "https://www.amazon.ca/s?k=Little%20West%20Street%20Cotton%20Baby%20Booties"
    }
   }
  ]
 },
 "15": {
  "ts": "2026-06-23",
  "seen": [
   "H&M Cotton Jersey Mittens",
   "FirstCry BabyHug Scratch Mittens",
   "Aden + Anais Essentials Muslin Mittens",
   "Kyte Baby Scratch Mittens",
   "Burt's Bees Baby Organic Cotton Mittens",
   "Mamas & Papas Essential Cotton Mittens"
  ],
  "list": [
   {
    "name": "Kyte Baby Scratch Mittens",
    "why": "Made from signature bamboo rayon which is temperature-regulating, perfect for transitioning into the Indian winter.",
    "pros": [
     "Extremely soft and gentle on sensitive skin",
     "Stays on well due to high-quality elastic"
    ],
    "cons": [
     "Higher price point due to international shipping/import"
    ],
    "price": 1800,
    "currency": "INR",
    "links": {
     "india": "https://www.amazon.in/s?k=Kyte%20Baby%20Scratch%20Mittens",
     "uk": "https://www.next.co.uk/search?w=Kyte%20Baby%20Scratch%20Mittens",
     "canada": "https://www.amazon.ca/s?k=Kyte%20Baby%20Scratch%20Mittens"
    }
   },
   {
    "name": "Burt's Bees Baby Organic Cotton Mittens",
    "why": "A gold standard for organic cotton that provides warmth without overheating, widely available in Canada and UK markets.",
    "pros": [
     "100% GOTS-certified organic cotton",
     "Durable fabric that withstands multiple washes"
    ],
    "cons": [
     "Can shrink slightly if tumble dried on high heat"
    ],
    "price": 1200,
    "currency": "INR",
    "links": {
     "india": "https://www.amazon.in/s?k=Burt's%20Bees%20Baby%20Organic%20Cotton%20Mittens",
     "uk": "https://www.next.co.uk/search?w=Burt's%20Bees%20Baby%20Organic%20Cotton%20Mittens",
     "canada": "https://www.amazon.ca/s?k=Burt's%20Bees%20Baby%20Organic%20Cotton%20Mittens"
    }
   },
   {
    "name": "Mamas & Papas Essential Cotton Mittens",
    "why": "Designed by a UK-based baby expert, these are practical and offer a reliable fit for newborns.",
    "pros": [
     "Excellent fit that doesn't slip off easily",
     "Simple, neutral designs that match most outfits"
    ],
    "cons": [
     "Less breathable than bamboo fabrics"
    ],
    "price": 950,
    "currency": "INR",
    "links": {
     "india": "https://www.amazon.in/s?k=Mamas%20%26%20Papas%20Essential%20Cotton%20Mittens",
     "uk": "https://www.next.co.uk/search?w=Mamas%20%26%20Papas%20Essential%20Cotton%20Mittens",
     "canada": "https://www.amazon.ca/s?k=Mamas%20%26%20Papas%20Essential%20Cotton%20Mittens"
    }
   }
  ]
 },
 "16": {
  "ts": "2026-06-23",
  "seen": [
   "Aden + Anais Essentials Hooded Towel",
   "The White Company Hydrocotton Hooded Baby Towel",
   "Pottery Barn Kids Organic Cotton Hooded Towel",
   "Little West Street Organic Cotton Hooded Towel",
   "Burt's Bees Baby Hooded Towel",
   "Mothercare Hooded Baby Towel"
  ],
  "list": [
   {
    "name": "Little West Street Organic Cotton Hooded Towel",
    "why": "A premium Indian brand offering soft, GOTS-certified organic cotton perfect for delicate newborn skin.",
    "pros": [
     "Extremely soft and absorbent",
     "Stylish and modern prints"
    ],
    "cons": [
     "Higher price point than local market options"
    ],
    "price": 1499,
    "currency": "INR",
    "links": {
     "india": "https://www.amazon.in/s?k=Little%20West%20Street%20Organic%20Cotton%20Hooded%20Towel",
     "uk": "https://www.next.co.uk/search?w=Little%20West%20Street%20Organic%20Cotton%20Hooded%20Towel",
     "canada": "https://www.amazon.ca/s?k=Little%20West%20Street%20Organic%20Cotton%20Hooded%20Towel"
    }
   },
   {
    "name": "Burt's Bees Baby Hooded Towel",
    "why": "Widely available in Canada/US markets, this towel is known for its durability and high-quality organic knit fabric.",
    "pros": [
     "Excellent thickness and warmth",
     "Retains softness after multiple washes"
    ],
    "cons": [
     "Limited availability in India without international shipping"
    ],
    "price": 2800,
    "currency": "INR",
    "links": {
     "india": "https://www.amazon.in/s?k=Burt's%20Bees%20Baby%20Hooded%20Towel",
     "uk": "https://www.next.co.uk/search?w=Burt's%20Bees%20Baby%20Hooded%20Towel",
     "canada": "https://www.amazon.ca/s?k=Burt's%20Bees%20Baby%20Hooded%20Towel"
    }
   },
   {
    "name": "Mothercare Hooded Baby Towel",
    "why": "A trusted global staple that is easily accessible in India and offers reliable quality for everyday winter use.",
    "pros": [
     "Very easy to source in major Indian cities",
     "Standard size fits newborns well"
    ],
    "cons": [
     "Can feel slightly thinner than luxury organic brands"
    ],
    "price": 999,
    "currency": "INR",
    "links": {
     "india": "https://www.amazon.in/s?k=Mothercare%20Hooded%20Baby%20Towel",
     "uk": "https://www.next.co.uk/search?w=Mothercare%20Hooded%20Baby%20Towel",
     "canada": "https://www.amazon.ca/s?k=Mothercare%20Hooded%20Baby%20Towel"
    }
   }
  ]
 },
 "17": {
  "ts": "2026-06-23",
  "seen": [
   "Mustela Gentle Cleansing Gel",
   "Mamaearth Deep Nourishing Baby Wash",
   "Baby Dove Rich Moisture Tip to Toe Wash",
   "Eucerin Baby Wash & Shampoo",
   "Pipette Baby Shampoo & Wash",
   "The Moms Co. Baby Wash"
  ],
  "list": [
   {
    "name": "Eucerin Baby Wash & Shampoo",
    "why": "Formulated specifically for sensitive, eczema-prone skin common in cooler, dry winter climates.",
    "pros": [
     "Soap-free and fragrance-free",
     "Very gentle on eyes"
    ],
    "cons": [
     "Less lather than standard washes"
    ],
    "price": 1800,
    "currency": "INR",
    "links": {
     "india": "https://www.amazon.in/s?k=Eucerin%20Baby%20Wash%20%26%20Shampoo",
     "uk": "https://www.next.co.uk/search?w=Eucerin%20Baby%20Wash%20%26%20Shampoo",
     "canada": "https://www.amazon.ca/s?k=Eucerin%20Baby%20Wash%20%26%20Shampoo"
    }
   },
   {
    "name": "Pipette Baby Shampoo & Wash",
    "why": "Uses sugarcane-derived squalane to mimic natural vernix, keeping newborn skin hydrated in winter.",
    "pros": [
     "Clean, non-toxic ingredients",
     "Hypoallergenic formula"
    ],
    "cons": [
     "Harder to find in local Indian retail stores"
    ],
    "price": 2200,
    "currency": "INR",
    "links": {
     "india": "https://www.amazon.in/s?k=Pipette%20Baby%20Shampoo%20%26%20Wash",
     "uk": "https://www.next.co.uk/search?w=Pipette%20Baby%20Shampoo%20%26%20Wash",
     "canada": "https://www.amazon.ca/s?k=Pipette%20Baby%20Shampoo%20%26%20Wash"
    }
   },
   {
    "name": "The Moms Co. Baby Wash",
    "why": "A highly-rated, locally available Indian brand that uses natural, tear-free ingredients suitable for delicate skin.",
    "pros": [
     "Easily accessible in India",
     "Contains organic argan and avocado oil"
    ],
    "cons": [
     "Bottle pump mechanism can sometimes clog"
    ],
    "price": 450,
    "currency": "INR",
    "links": {
     "india": "https://www.amazon.in/s?k=The%20Moms%20Co.%20Baby%20Wash",
     "uk": "https://www.next.co.uk/search?w=The%20Moms%20Co.%20Baby%20Wash",
     "canada": "https://www.amazon.ca/s?k=The%20Moms%20Co.%20Baby%20Wash"
    }
   }
  ]
 },
 "18": {
  "ts": "2026-06-23",
  "seen": [
   "Aveeno Baby Wash & Shampoo",
   "Cetaphil Baby Wash & Shampoo",
   "Pipette Baby Shampoo & Wash",
   "Baby Dove Sensitive Moisture Tip to Toe Wash",
   "La Roche-Posay Lipikar Gel Lavant",
   "Mamaearth Deeply Nourishing Baby Wash"
  ],
  "list": [
   {
    "name": "Baby Dove Sensitive Moisture Tip to Toe Wash",
    "why": "Formulated with 1/4 moisturizing cream, it is exceptionally gentle for newborns in dry winter months.",
    "pros": [
     "Hypoallergenic and tear-free",
     "Very affordable and widely available"
    ],
    "cons": [
     "Contains fragrance which may irritate extremely sensitive skin"
    ],
    "price": 350,
    "currency": "INR",
    "links": {
     "india": "https://www.amazon.in/s?k=Baby%20Dove%20Sensitive%20Moisture%20Tip%20to%20Toe%20Wash",
     "uk": "https://www.next.co.uk/search?w=Baby%20Dove%20Sensitive%20Moisture%20Tip%20to%20Toe%20Wash",
     "canada": "https://www.amazon.ca/s?k=Baby%20Dove%20Sensitive%20Moisture%20Tip%20to%20Toe%20Wash"
    }
   },
   {
    "name": "La Roche-Posay Lipikar Gel Lavant",
    "why": "A premium soap-free formula designed for sensitive, dry, or eczema-prone skin, perfect for harsh winter air.",
    "pros": [
     "Contains Niacinamide and Shea Butter",
     "Excellent for soothing irritated skin"
    ],
    "cons": [
     "Higher price point compared to standard baby brands"
    ],
    "price": 1800,
    "currency": "INR",
    "links": {
     "india": "https://www.amazon.in/s?k=La%20Roche-Posay%20Lipikar%20Gel%20Lavant",
     "uk": "https://www.next.co.uk/search?w=La%20Roche-Posay%20Lipikar%20Gel%20Lavant",
     "canada": "https://www.amazon.ca/s?k=La%20Roche-Posay%20Lipikar%20Gel%20Lavant"
    }
   },
   {
    "name": "Mamaearth Deeply Nourishing Baby Wash",
    "why": "Infused with natural ingredients like aloe vera and jojoba oil, it is a popular, accessible choice in India.",
    "pros": [
     "Tear-free and toxin-free formula",
     "Readily available in almost all retail outlets"
    ],
    "cons": [
     "Not as effective for severe eczema as medical-grade brands"
    ],
    "price": 400,
    "currency": "INR",
    "links": {
     "india": "https://www.amazon.in/s?k=Mamaearth%20Deeply%20Nourishing%20Baby%20Wash",
     "uk": "https://www.next.co.uk/search?w=Mamaearth%20Deeply%20Nourishing%20Baby%20Wash",
     "canada": "https://www.amazon.ca/s?k=Mamaearth%20Deeply%20Nourishing%20Baby%20Wash"
    }
   }
  ]
 }
}